zodb.py3migrate-0.6-py2.7-nspkg.pth
zodb/py3migrate/__init__.py
zodb/py3migrate/analyze.py
zodb/py3migrate/conftest.py
zodb/py3migrate/convert.py
zodb/py3migrate/magic.py
zodb/py3migrate/migrate.py
zodb/py3migrate/testing.py
zodb/py3migrate/tests/__init__.py
zodb/py3migrate/tests/test_analyze.py
zodb/py3migrate/tests/test_convert.py
zodb/py3migrate/tests/test_magic.py
zodb/py3migrate/tests/test_migrate.py
zodb.py3migrate-0.6.data/data/CHANGES.rst
zodb.py3migrate-0.6.data/data/HACKING.rst
zodb.py3migrate-0.6.data/data/LICENSE.txt
zodb.py3migrate-0.6.data/data/README.rst
zodb.py3migrate-0.6.data/data/requirements-doc.txt
zodb.py3migrate-0.6.dist-info/DESCRIPTION.rst
zodb.py3migrate-0.6.dist-info/METADATA
zodb.py3migrate-0.6.dist-info/RECORD
zodb.py3migrate-0.6.dist-info/WHEEL
zodb.py3migrate-0.6.dist-info/entry_points.txt
zodb.py3migrate-0.6.dist-info/metadata.json
zodb.py3migrate-0.6.dist-info/namespace_packages.txt
zodb.py3migrate-0.6.dist-info/top_level.txt
