Metadata-Version: 2.0
Name: zodb.py3migrate
Version: 0.6
Summary: Helper to check if ZODB is Python 3 ready by displaying binary fields that might need conversion to unicode.
Home-page: https://github.com/gocept/zodb.py3migrate/
Author: gocept <mail@gocept.com>
Author-email: mail@gocept.com
License: MIT License
Keywords: zodb python3
Platform: UNKNOWN
Classifier: License :: OSI Approved
Classifier: License :: OSI Approved :: MIT License
Classifier: Programming Language :: Python
Classifier: Programming Language :: Python :: 2
Classifier: Programming Language :: Python :: 2.7
Classifier: Programming Language :: Python :: Implementation :: CPython
Provides-Extra: test
Requires-Dist: ZODB3 (>=3.11)
Requires-Dist: setuptools
Requires-Dist: zodbpickle
Provides-Extra: test
Requires-Dist: Products.PythonScripts; extra == 'test'
Requires-Dist: mock; extra == 'test'
Requires-Dist: pytest; extra == 'test'
Requires-Dist: transaction; extra == 'test'
